configapi/__init__.py
configapi/configs.py
configapi/patcher.py
configapi/scope.py
configapi/sources.py
configapi/toml.py
configapi/types.py
configapi-0.0.7.dist-info/METADATA
configapi-0.0.7.dist-info/WHEEL
configapi-0.0.7.dist-info/top_level.txt
configapi-0.0.7.dist-info/RECORD
