Metadata-Version: 2.2
Name: configapi
Version: 0.0.7
Summary: A dict-style API for TOML-based config files.
Author-email: Patrick Schaffner <patrick.schaffner@protonmail.ch>
Maintainer-email: Patrick Schaffner <patrick.schaffner@protonmail.ch>
License: MIT License
Project-URL: Source, https://github.com/PatrickSchaffner/ConfigAPI
Keywords: configs,toml,dict
Requires-Python: >=3.8
Requires-Dist: tomli
Requires-Dist: tomli_w
Requires-Dist: packaging
Provides-Extra: test
Requires-Dist: pytest; extra == "test"
Requires-Dist: pytest-cov; extra == "test"
Requires-Dist: pyfakefs; extra == "test"
